vibe_llama/__init__.py
vibe_llama/logo.py
vibe_llama/main.py
vibe_llama/docuflows/__init__.py
vibe_llama/docuflows/cli.py
vibe_llama/docuflows/agent/__init__.py
vibe_llama/docuflows/agent/utils.py
vibe_llama/docuflows/commons/__init__.py
vibe_llama/docuflows/commons/constants.py
vibe_llama/docuflows/commons/core.py
vibe_llama/docuflows/commons/typed_state.py
vibe_llama/docuflows/commons/typed_state_editing.py
vibe_llama/docuflows/editing/__init__.py
vibe_llama/docuflows/handlers/__init__.py
vibe_llama/docuflows/handlers/workflow_config.py
vibe_llama/docuflows/handlers/workflow_editing.py
vibe_llama/docuflows/handlers/workflow_generation.py
vibe_llama/docuflows/handlers/workflow_help.py
vibe_llama/docuflows/handlers/workflow_load.py
vibe_llama/docuflows/handlers/workflow_testing.py
vibe_llama/docuflows/prompts/__init__.py
vibe_llama/docuflows/tools/__init__.py
vibe_llama/scaffold/__init__.py
vibe_llama/scaffold/terminal.py
vibe_llama/sdk/__init__.py
vibe_llama/sdk/base.py
vibe_llama/sdk/errors.py
vibe_llama/sdk/mcp.py
vibe_llama/sdk/utils.py
vibe_llama/starter/__init__.py
vibe_llama/starter/mcp.py
vibe_llama/starter/terminal.py
vibe_llama/starter/utils.py
vibe_llama-0.5.1.dist-info/METADATA
vibe_llama-0.5.1.dist-info/WHEEL
vibe_llama-0.5.1.dist-info/entry_points.txt
vibe_llama-0.5.1.dist-info/licenses/LICENSE
vibe_llama-0.5.1.dist-info/RECORD
