Metadata-Version: 2.4
Name: vibe-llama
Version: 0.5.1
Summary: vibe-llama is a set of tools that are designed to help developers build working and reliable applications with LlamaIndex, LlamaCloud Services and llama-index-workflows.
License-File: LICENSE
Requires-Python: >=3.10
Requires-Dist: bm25s>=0.2.13
Requires-Dist: fastmcp>=2.11.3
Requires-Dist: llama-cloud-services>=0.6.62
Requires-Dist: llama-index-core>=0.13.3
Requires-Dist: llama-index-llms-anthropic>=0.8.4
Requires-Dist: llama-index-llms-openai>=0.5.4
Requires-Dist: prompt-toolkit>=3.0.51
Requires-Dist: pystemmer>=3.0.0
Requires-Dist: rich-gradient>=0.3.3
Requires-Dist: rich>=14.1.0
Requires-Dist: tomli-w>=1.2.0
Requires-Dist: vibe-llama-core>=0.2.1
